greatx/__init__.py
greatx/version.py
greatx/attack/__init__.py
greatx/attack/attacker.py
greatx/attack/flip_attacker.py
greatx/attack/backdoor/__init__.py
greatx/attack/backdoor/backdoor_attacker.py
greatx/attack/backdoor/lgc_backdoor.py
greatx/attack/injection/__init__.py
greatx/attack/injection/adv_injection.py
greatx/attack/injection/injection_attacker.py
greatx/attack/injection/random_injection.py
greatx/attack/targeted/__init__.py
greatx/attack/targeted/dice_attack.py
greatx/attack/targeted/fg_attack.py
greatx/attack/targeted/gf_attack.py
greatx/attack/targeted/ig_attack.py
greatx/attack/targeted/nettack.py
greatx/attack/targeted/random_attack.py
greatx/attack/targeted/sg_attack.py
greatx/attack/targeted/targeted_attacker.py
greatx/attack/untargeted/__init__.py
greatx/attack/untargeted/dice_attack.py
greatx/attack/untargeted/fg_attack.py
greatx/attack/untargeted/ig_attack.py
greatx/attack/untargeted/metattack.py
greatx/attack/untargeted/pgd_attack.py
greatx/attack/untargeted/random_attack.py
greatx/attack/untargeted/untargeted_attacker.py
greatx/datasets/__init__.py
greatx/datasets/graph_dataset.py
greatx/defense/__init__.py
greatx/defense/feature_propagation.py
greatx/defense/gnnguard.py
greatx/defense/purification.py
greatx/defense/universal_defense.py
greatx/functional/__init__.py
greatx/functional/dropouts.py
greatx/functional/spmm.py
greatx/functional/transform.py
greatx/nn/__init__.py
greatx/nn/layers/__init__.py
greatx/nn/layers/activations.py
greatx/nn/layers/adaptive_conv.py
greatx/nn/layers/container.py
greatx/nn/layers/dagnn_conv.py
greatx/nn/layers/dg_conv.py
greatx/nn/layers/dropouts.py
greatx/nn/layers/elastic_conv.py
greatx/nn/layers/gcn_conv.py
greatx/nn/layers/median_conv.py
greatx/nn/layers/robust_conv.py
greatx/nn/layers/sat_conv.py
greatx/nn/layers/sg_conv.py
greatx/nn/layers/soft_median_conv.py
greatx/nn/layers/ssg_conv.py
greatx/nn/layers/tag_conv.py
greatx/nn/layers/tensor_conv.py
greatx/nn/models/__init__.py
greatx-0.0.1b0.dist-info/LICENSE
greatx-0.0.1b0.dist-info/METADATA
greatx-0.0.1b0.dist-info/WHEEL
greatx-0.0.1b0.dist-info/top_level.txt
greatx-0.0.1b0.dist-info/RECORD
